iwut/__init__.py
wai/__init__.py
wat/__init__.py
iwut-0.0.4.dist-info/LICENSE
iwut-0.0.4.dist-info/METADATA
iwut-0.0.4.dist-info/WHEEL
iwut-0.0.4.dist-info/top_level.txt
iwut-0.0.4.dist-info/RECORD
