Metadata-Version: 2.1
Name: iwut
Version: 0.0.4
Summary: Friendlier tracebacks, collapsing frames with library code,inline variable values, and adding context
Home-page: https://pypi.python.org/pypi/wut
Author: Alvin Wan
Author-email: hi@alvinwan.com
License: MIT
Keywords: ipython traceback error exception
Platform: UNKNOWN
Classifier: Topic :: Utilities
Classifier: Intended Audience :: Developers
Classifier: Development Status :: 3 - Alpha
Classifier: Environment :: Console
Classifier: License :: OSI Approved :: MIT License
Classifier: Programming Language :: Python :: 3
Requires-Dist: ipython (>=1.0)
